Hu_App/__init__.py
Hu_App/create_topic.py
Hu_App/delete_topic.py
Hu_App-1.3.data/data/topics.yaml
Hu_App-1.3.dist-info/METADATA
Hu_App-1.3.dist-info/WHEEL
Hu_App-1.3.dist-info/top_level.txt
Hu_App-1.3.dist-info/RECORD
